{
    "version": "2.3.0",
    "architecture": {
        "32bit": {
            "url": "https://github.com/gembaadvantage/uplift/releases/download/v2.3.0/uplift_2.3.0_windows-i386.zip",
            "bin": [
                "uplift.exe"
            ],
            "hash": "e9fe2a66907e6e5661a388c3172ad2de63079d7a3ac696d1bfcd27a2e8d95cae"
        },
        "64bit": {
            "url": "https://github.com/gembaadvantage/uplift/releases/download/v2.3.0/uplift_2.3.0_windows-x86_64.zip",
            "bin": [
                "uplift.exe"
            ],
            "hash": "afa241cb11756c55bd81ee0651d122f0dcac0f0ac2020eaa637534b0247390a4"
        }
    },
    "homepage": "https://github.com/gembaadvantage/uplift",
    "license": "MIT",
    "description": "Semantic versioning the easy way"
}